Workbook

Sheet Assumptions
A1: Beer-Adjacent Desk Objects — Low-MOQ Sourcing Model
A2: All costs are Claude estimates for planning (typical 2026 small-batch / POD vendor ranges), not vendor quotes. Numbers from Mike: none yet.
A4: Global levers
A5: Inbound freight, % of unit cost | B5: 0.18 | C5: Small-batch air/ePacket from overseas fabs; ~5-8% if sourced domestic
A6: Duty + import fees, % of unit cost | B6: 0.07 | C6: Blended estimate; ceramics/metal vary 0-9%
A7: Defect / breakage allowance, % | B7: 0.05 | C7: Ceramics & resin dominate the lineup
A8: Fulfillment cost per order ($) | B8: 5.5 | C8: Pick/pack + domestic ship, small parcel
A9: Assumed sell rate, units / product / month | B9: 12 | C9: Conservative early Etsy/site pace
A11: Legend
A12: Blue text on yellow | B12: Editable input / assumption — change these
A13: Black text | B13: Formula — do not overwrite
A14: Green text | B14: Pulls from another sheet

Sheet Sourcing Model
A1: Product | B1: Batch | C1: Sourcing route | D1: MOQ (units) | E1: Tooling / setup ($) | F1: Unit cost @ MOQ ($) | G1: Landed unit cost ($) | H1: Retail price ($) | I1: Gross margin (%) | J1: MOQ cash outlay ($) | K1: Break-even (units) | L1: Months to break even
A2: Wave Plinth (can pedestal) | B2: 1 | C2: Small-batch ceramics studio | D2: 50 | E2: 250 | F2: 6.5 | G2: =F2*(1+Assumptions!$B$5+Assumptions!$B$6+Assumptions!$B$7) | H2: 34 | I2: =IF(H2=0,0,(H2-G2-Assumptions!$B$8)/H2) | J2: =E2+D2*F2 | K2: =IF((H2-G2-Assumptions!$B$8)<=0,0,J2/(H2-G2-Assumptions!$B$8)) | L2: =IF(Assumptions!$B$9=0,0,K2/Assumptions!$B$9)
A3: Tidepool Coaster | B3: 1 | C3: In-house resin casting | D3: 25 | E3: 180 | F3: 4.2 | G3: =F3*(1+Assumptions!$B$5+Assumptions!$B$6+Assumptions!$B$7) | H3: 24 | I3: =IF(H3=0,0,(H3-G3-Assumptions!$B$8)/H3) | J3: =E3+D3*F3 | K3: =IF((H3-G3-Assumptions!$B$8)<=0,0,J3/(H3-G3-Assumptions!$B$8)) | L3: =IF(Assumptions!$B$9=0,0,K3/Assumptions!$B$9)
A4: Snack Butte (terraced dish) | B4: 1 | C4: Small-batch ceramics studio | D4: 50 | E4: 300 | F4: 8 | G4: =F4*(1+Assumptions!$B$5+Assumptions!$B$6+Assumptions!$B$7) | H4: 42 | I4: =IF(H4=0,0,(H4-G4-Assumptions!$B$8)/H4) | J4: =E4+D4*F4 | K4: =IF((H4-G4-Assumptions!$B$8)<=0,0,J4/(H4-G4-Assumptions!$B$8)) | L4: =IF(Assumptions!$B$9=0,0,K4/Assumptions!$B$9)
A5: Cap Dominoes (tile game set) | B5: 1 | C5: Local print + laminate | D5: 25 | E5: 60 | F5: 5.5 | G5: =F5*(1+Assumptions!$B$5+Assumptions!$B$6+Assumptions!$B$7) | H5: 28 | I5: =IF(H5=0,0,(H5-G5-Assumptions!$B$8)/H5) | J5: =E5+D5*F5 | K5: =IF((H5-G5-Assumptions!$B$8)<=0,0,J5/(H5-G5-Assumptions!$B$8)) | L5: =IF(Assumptions!$B$9=0,0,K5/Assumptions!$B$9)
A6: Weighted Wave Block | B6: 1 | C6: Acrylic embedment fab | D6: 50 | E6: 200 | F6: 9 | G6: =F6*(1+Assumptions!$B$5+Assumptions!$B$6+Assumptions!$B$7) | H6: 48 | I6: =IF(H6=0,0,(H6-G6-Assumptions!$B$8)/H6) | J6: =E6+D6*F6 | K6: =IF((H6-G6-Assumptions!$B$8)<=0,0,J6/(H6-G6-Assumptions!$B$8)) | L6: =IF(Assumptions!$B$9=0,0,K6/Assumptions!$B$9)
A7: Cap Crane (desk gadget) | B7: 1 | C7: 3D print + hardware kit | D7: 25 | E7: 120 | F7: 11 | G7: =F7*(1+Assumptions!$B$5+Assumptions!$B$6+Assumptions!$B$7) | H7: 55 | I7: =IF(H7=0,0,(H7-G7-Assumptions!$B$8)/H7) | J7: =E7+D7*F7 | K7: =IF((H7-G7-Assumptions!$B$8)<=0,0,J7/(H7-G7-Assumptions!$B$8)) | L7: =IF(Assumptions!$B$9=0,0,K7/Assumptions!$B$9)
A8: Beer Archive Blocks | B8: 1 | C8: Laser-cut acrylic shop | D8: 25 | E8: 90 | F8: 6 | G8: =F8*(1+Assumptions!$B$5+Assumptions!$B$6+Assumptions!$B$7) | H8: 30 | I8: =IF(H8=0,0,(H8-G8-Assumptions!$B$8)/H8) | J8: =E8+D8*F8 | K8: =IF((H8-G8-Assumptions!$B$8)<=0,0,J8/(H8-G8-Assumptions!$B$8)) | L8: =IF(Assumptions!$B$9=0,0,K8/Assumptions!$B$9)
A9: Featured-Exhibit Easel | B9: 1 | C9: Laser-cut wood shop | D9: 25 | E9: 70 | F9: 3.5 | G9: =F9*(1+Assumptions!$B$5+Assumptions!$B$6+Assumptions!$B$7) | H9: 18 | I9: =IF(H9=0,0,(H9-G9-Assumptions!$B$8)/H9) | J9: =E9+D9*F9 | K9: =IF((H9-G9-Assumptions!$B$8)<=0,0,J9/(H9-G9-Assumptions!$B$8)) | L9: =IF(Assumptions!$B$9=0,0,K9/Assumptions!$B$9)
A10: Backlit Wave Tile | B10: 1 | C10: Print + LED puck assembly | D10: 25 | E10: 80 | F10: 7.5 | G10: =F10*(1+Assumptions!$B$5+Assumptions!$B$6+Assumptions!$B$7) | H10: 38 | I10: =IF(H10=0,0,(H10-G10-Assumptions!$B$8)/H10) | J10: =E10+D10*F10 | K10: =IF((H10-G10-Assumptions!$B$8)<=0,0,J10/(H10-G10-Assumptions!$B$8)) | L10: =IF(Assumptions!$B$9=0,0,K10/Assumptions!$B$9)
A11: Tide Line Tray (can rack) | B11: 1 | C11: Small-batch ceramics studio | D11: 50 | E11: 350 | F11: 12 | G11: =F11*(1+Assumptions!$B$5+Assumptions!$B$6+Assumptions!$B$7) | H11: 58 | I11: =IF(H11=0,0,(H11-G11-Assumptions!$B$8)/H11) | J11: =E11+D11*F11 | K11: =IF((H11-G11-Assumptions!$B$8)<=0,0,J11/(H11-G11-Assumptions!$B$8)) | L11: =IF(Assumptions!$B$9=0,0,K11/Assumptions!$B$9)
A12: Tide Chart Coasters (cork) | B12: 2 | C12: Cork print-on-demand | D12: 50 | E12: 40 | F12: 2.8 | G12: =F12*(1+Assumptions!$B$5+Assumptions!$B$6+Assumptions!$B$7) | H12: 16 | I12: =IF(H12=0,0,(H12-G12-Assumptions!$B$8)/H12) | J12: =E12+D12*F12 | K12: =IF((H12-G12-Assumptions!$B$8)<=0,0,J12/(H12-G12-Assumptions!$B$8)) | L12: =IF(Assumptions!$B$9=0,0,K12/Assumptions!$B$9)
A13: Crest Opener (brass, plaque) | B13: 2 | C13: Overseas metal fab | D13: 100 | E13: 400 | F13: 7 | G13: =F13*(1+Assumptions!$B$5+Assumptions!$B$6+Assumptions!$B$7) | H13: 36 | I13: =IF(H13=0,0,(H13-G13-Assumptions!$B$8)/H13) | J13: =E13+D13*F13 | K13: =IF((H13-G13-Assumptions!$B$8)<=0,0,J13/(H13-G13-Assumptions!$B$8)) | L13: =IF(Assumptions!$B$9=0,0,K13/Assumptions!$B$9)
... A21: Pier Piling Koozie | B21: 2 | C21: Custom neoprene fab | D21: 100 | E21: 110 | F21: 2.6 | G21: =F21*(1+Assumptions!$B$5+Assumptions!$B$6+Assumptions!$B$7) | H21: 14 | I21: =IF(H21=0,0,(H21-G21-Assumptions!$B$8)/H21) | J21: =E21+D21*F21 | K21: =IF((H21-G21-Assumptions!$B$8)<=0,0,J21/(H21-G21-Assumptions!$B$8)) | L21: =IF(Assumptions!$B$9=0,0,K21/Assumptions!$B$9)
A23: PORTFOLIO TOTAL / AVG | I23: =AVERAGE(I2:I21) | J23: =SUM(J2:J21) | K23: =SUM(K2:K21)
A24: Total cash to produce all 20 at MOQ ->
